nexios_generic/__init__.py
nexios_generic/base.py
nexios_generic/mixins.py
nexios_generic/views.py
nexios_generic-0.1.1.dist-info/METADATA
nexios_generic-0.1.1.dist-info/WHEEL
nexios_generic-0.1.1.dist-info/RECORD
