Metadata-Version: 2.3
Name: nexios-generic
Version: 0.1.1
Summary: Nexios-Generic is an extension for the Nexios framework that provides a class-based view implementation, integrating seamlessly with Tortoise ORM and Pydantic for efficient, structured API development. It simplifies request handling, validation, and database interactions, enabling a more declarative and reusable approach to building Nexios applications.
License: BSD-3-Clause
Author: dunamix
Author-email: techwithdunamix@gmail.com
Requires-Python: >=3.9
Classifier: License :: OSI Approved :: BSD License
Classifier: Programming Language :: Python :: 3
Classifier: Programming Language :: Python :: 3.9
Classifier: Programming Language :: Python :: 3.10
Classifier: Programming Language :: Python :: 3.11
Classifier: Programming Language :: Python :: 3.12
Classifier: Programming Language :: Python :: 3.13
Requires-Dist: nexios (>=2.2.4)
